habitatsuitability/__init__.py
habitatsuitability/config.py
habitatsuitability/scripts.py
habitatsuitability/hsi_raster/__init__.py
habitatsuitability/hsi_raster/flusstools_geotools_functions.py
habitatsuitability/hsi_raster/hsi_raster_fun.py
habitatsuitability/hsi_raster/raster.py
habitatsuitability/hsi_raster/raster_hsi.py
habitatsuitability/tools/__init__.py
habitatsuitability/tools/binning.py
habitatsuitability/tools/bio_evaluation_fun.py
habitatsuitability/tools/bio_tools.py
habitatsuitability/tools/bioverification_fun.py
habitatsuitability/tools/fun.py
habitatsuitability/tools/input_data_testing.py
habitatsuitability/tools/visualization.py
habitat_suitability-0.0.6.dist-info/LICENSE
habitat_suitability-0.0.6.dist-info/METADATA
habitat_suitability-0.0.6.dist-info/WHEEL
habitat_suitability-0.0.6.dist-info/top_level.txt
habitat_suitability-0.0.6.dist-info/RECORD
